setup.cfg
setup.py
docs/HISTORY.txt
infrae/__init__.py
infrae.plone.relations.form.egg-info/PKG-INFO
infrae.plone.relations.form.egg-info/SOURCES.txt
infrae.plone.relations.form.egg-info/dependency_links.txt
infrae.plone.relations.form.egg-info/namespace_packages.txt
infrae.plone.relations.form.egg-info/not-zip-safe
infrae.plone.relations.form.egg-info/requires.txt
infrae.plone.relations.form.egg-info/top_level.txt
infrae/plone/__init__.py
infrae/plone/relations/__init__.py
infrae/plone/relations/form/README.EXT.txt
infrae/plone/relations/form/README.txt
infrae/plone/relations/form/__init__.py
infrae/plone/relations/form/_add.py
infrae/plone/relations/form/_context.py
infrae/plone/relations/form/_objectid.py
infrae/plone/relations/form/_view.py
infrae/plone/relations/form/_widget.py
infrae/plone/relations/form/addrelation_list.pt
infrae/plone/relations/form/addrelation_search.pt
infrae/plone/relations/form/addrelation_vocabulary.pt
infrae/plone/relations/form/configure.zcml
infrae/plone/relations/form/editcontext.pt
infrae/plone/relations/form/example.py
infrae/plone/relations/form/interfaces.py
infrae/plone/relations/form/plonerelation.css
infrae/plone/relations/form/plonerelation_edit.pt
infrae/plone/relations/form/plonerelation_view.pt
infrae/plone/relations/form/tests.py
infrae/plone/relations/form/utility.py