Metadata-Version: 1.0
Name: infrae.plone.relations.form
Version: 0.9
Summary: Formlib widget to manage plone.app.relations relations in a plone site.
Home-page: http://svn.infrae.com/PloneComponent/infrae.plone.relations.form/trunk
Author: Sylvain Viollon
Author-email: sylvain@infrae.com
License: GPL
Keywords: relationships plone widget formlib
Platform: UNKNOWN
Classifier: Framework :: Plone
Classifier: Framework :: Zope2
Classifier: Programming Language :: Python
Classifier: Topic :: Software Development :: Libraries :: Python Modules
